{
  "v": "5.6.9",
  "fr": 60,
  "ip": 0,
  "op": 240,
  "w": 720,
  "h": 160,
  "nm": "托盘",
  "ddd": 0,
  "assets": [
    {
      "id": "image_0",
      "w": 500,
      "h": 134,
      "u": "images/",
      "p": "img_0.png",
      "e": 0
    },
    {
      "id": "image_1",
      "w": 71,
      "h": 57,
      "u": "images/",
      "p": "img_1.png",
      "e": 0
    }
  ],
  "layers": [
    {
      "ddd": 0,
      "ind": 1,
      "ty": 2,
      "nm": "千库网_金色光效元素_元素编号12404498.png",
      "cl": "png",
      "refId": "image_0",
      "sr": 1,
      "ks": {
        "o": {
          "a": 1,
          "k": [
            {
              "i": {
                "x": [
                  0.667
                ],
                "y": [
                  1
                ]
              },
              "o": {
                "x": [
                  0.333
                ],
                "y": [
                  0
                ]
              },
              "t": 81,
              "s": [
                0
              ]
            },
            {
              "i": {
                "x": [
                  0.667
                ],
                "y": [
                  1
                ]
              },
              "o": {
                "x": [
                  0.333
                ],
                "y": [
                  0
                ]
              },
              "t": 125.297,
              "s": [
                100
              ]
            },
            {
              "t": 173,
              "s": [
                0
              ]
            }
          ],
          "ix": 11
        },
        "r": {
          "a": 0,
          "k": 0,
          "ix": 10
        },
        "p": {
          "a": 0,
          "k": [
            592,
            104.5,
            0
          ],
          "ix": 2
        },
        "a": {
          "a": 0,
          "k": [
            250,
            67,
            0
          ],
          "ix": 1
        },
        "s": {
          "a": 0,
          "k": [
            44,
            44,
            100
          ],
          "ix": 6
        }
      },
      "ao": 0,
      "ip": 34,
      "op": 274,
      "st": 34,
      "bm": 0
    },
    {
      "ddd": 0,
      "ind": 2,
      "ty": 2,
      "nm": "千库网_金色光效元素_元素编号12404498.png",
      "cl": "png",
      "refId": "image_0",
      "sr": 1,
      "ks": {
        "o": {
          "a": 1,
          "k": [
            {
              "i": {
                "x": [
                  0.667
                ],
                "y": [
                  1
                ]
              },
              "o": {
                "x": [
                  0.333
                ],
                "y": [
                  0
                ]
              },
              "t": 20,
              "s": [
                0
              ]
            },
            {
              "i": {
                "x": [
                  0.667
                ],
                "y": [
                  1
                ]
              },
              "o": {
                "x": [
                  0.333
                ],
                "y": [
                  0
                ]
              },
              "t": 64.297,
              "s": [
                100
              ]
            },
            {
              "t": 112,
              "s": [
                0
              ]
            }
          ],
          "ix": 11
        },
        "r": {
          "a": 0,
          "k": 0,
          "ix": 10
        },
        "p": {
          "a": 0,
          "k": [
            119,
            100,
            0
          ],
          "ix": 2
        },
        "a": {
          "a": 0,
          "k": [
            250,
            67,
            0
          ],
          "ix": 1
        },
        "s": {
          "a": 0,
          "k": [
            56,
            56,
            100
          ],
          "ix": 6
        }
      },
      "ao": 0,
      "ip": -27,
      "op": 213,
      "st": -27,
      "bm": 0
    },
    {
      "ddd": 0,
      "ind": 3,
      "ty": 2,
      "nm": "千库网_金色光效元素_元素编号12404498.png",
      "cl": "png",
      "refId": "image_0",
      "sr": 1,
      "ks": {
        "o": {
          "a": 1,
          "k": [
            {
              "i": {
                "x": [
                  0.667
                ],
                "y": [
                  1
                ]
              },
              "o": {
                "x": [
                  0.333
                ],
                "y": [
                  0
                ]
              },
              "t": 47,
              "s": [
                0
              ]
            },
            {
              "i": {
                "x": [
                  0.667
                ],
                "y": [
                  1
                ]
              },
              "o": {
                "x": [
                  0.333
                ],
                "y": [
                  0
                ]
              },
              "t": 91.297,
              "s": [
                100
              ]
            },
            {
              "t": 139,
              "s": [
                0
              ]
            }
          ],
          "ix": 11
        },
        "r": {
          "a": 0,
          "k": 0,
          "ix": 10
        },
        "p": {
          "a": 0,
          "k": [
            460,
            46,
            0
          ],
          "ix": 2
        },
        "a": {
          "a": 0,
          "k": [
            250,
            67,
            0
          ],
          "ix": 1
        },
        "s": {
          "a": 0,
          "k": [
            56,
            56,
            100
          ],
          "ix": 6
        }
      },
      "ao": 0,
      "ip": 0,
      "op": 240,
      "st": 0,
      "bm": 0
    },
    {
      "ddd": 0,
      "ind": 4,
      "ty": 2,
      "nm": "路径 7备份 2.png",
      "cl": "png",
      "refId": "image_1",
      "sr": 1,
      "ks": {
        "o": {
          "a": 1,
          "k": [
            {
              "i": {
                "x": [
                  0.667
                ],
                "y": [
                  1
                ]
              },
              "o": {
                "x": [
                  0.333
                ],
                "y": [
                  0
                ]
              },
              "t": 21.543,
              "s": [
                0
              ]
            },
            {
              "t": 42,
              "s": [
                60
              ]
            }
          ],
          "ix": 11
        },
        "r": {
          "a": 0,
          "k": 0,
          "ix": 10
        },
        "p": {
          "a": 1,
          "k": [
            {
              "i": {
                "x": 0.667,
                "y": 1
              },
              "o": {
                "x": 0.333,
                "y": 0
              },
              "t": 22,
              "s": [
                407.714,
                80,
                0
              ],
              "to": [
                20.798,
                -0.458,
                0
              ],
              "ti": [
                -20.798,
                0.458,
                0
              ]
            },
            {
              "t": 42,
              "s": [
                532.5,
                77.25,
                0
              ]
            }
          ],
          "ix": 2
        },
        "a": {
          "a": 0,
          "k": [
            35.5,
            28.5,
            0
          ],
          "ix": 1
        },
        "s": {
          "a": 0,
          "k": [
            100,
            100,
            100
          ],
          "ix": 6
        }
      },
      "ao": 0,
      "ip": 0,
      "op": 240,
      "st": 0,
      "bm": 0
    },
    {
      "ddd": 0,
      "ind": 5,
      "ty": 2,
      "nm": "路径 7备份 2.png",
      "cl": "png",
      "refId": "image_1",
      "sr": 1,
      "ks": {
        "o": {
          "a": 1,
          "k": [
            {
              "i": {
                "x": [
                  0.667
                ],
                "y": [
                  1
                ]
              },
              "o": {
                "x": [
                  0.333
                ],
                "y": [
                  0
                ]
              },
              "t": 27,
              "s": [
                0
              ]
            },
            {
              "t": 48,
              "s": [
                40
              ]
            }
          ],
          "ix": 11
        },
        "r": {
          "a": 0,
          "k": 0,
          "ix": 10
        },
        "p": {
          "a": 1,
          "k": [
            {
              "i": {
                "x": 0.667,
                "y": 1
              },
              "o": {
                "x": 0.333,
                "y": 0
              },
              "t": 27,
              "s": [
                358.5,
                80,
                0
              ],
              "to": [
                20.833,
                -0.5,
                0
              ],
              "ti": [
                0,
                0,
                0
              ]
            },
            {
              "t": 48,
              "s": [
                483.5,
                77,
                0
              ]
            }
          ],
          "ix": 2
        },
        "a": {
          "a": 0,
          "k": [
            35.5,
            28.5,
            0
          ],
          "ix": 1
        },
        "s": {
          "a": 0,
          "k": [
            100,
            100,
            100
          ],
          "ix": 6
        }
      },
      "ao": 0,
      "ip": 0,
      "op": 240,
      "st": 0,
      "bm": 0
    },
    {
      "ddd": 0,
      "ind": 6,
      "ty": 2,
      "nm": "路径 7备份 2.png",
      "cl": "png",
      "refId": "image_1",
      "sr": 1,
      "ks": {
        "o": {
          "a": 1,
          "k": [
            {
              "i": {
                "x": [
                  0.667
                ],
                "y": [
                  1
                ]
              },
              "o": {
                "x": [
                  0.333
                ],
                "y": [
                  0
                ]
              },
              "t": 31,
              "s": [
                0
              ]
            },
            {
              "t": 52,
              "s": [
                20
              ]
            }
          ],
          "ix": 11
        },
        "r": {
          "a": 0,
          "k": 0,
          "ix": 10
        },
        "p": {
          "a": 1,
          "k": [
            {
              "i": {
                "x": 0.667,
                "y": 1
              },
              "o": {
                "x": 0.333,
                "y": 0
              },
              "t": 31,
              "s": [
                309.5,
                80,
                0
              ],
              "to": [
                20.833,
                -0.5,
                0
              ],
              "ti": [
                -20.833,
                0.5,
                0
              ]
            },
            {
              "t": 52,
              "s": [
                434.5,
                77,
                0
              ]
            }
          ],
          "ix": 2
        },
        "a": {
          "a": 0,
          "k": [
            35.5,
            28.5,
            0
          ],
          "ix": 1
        },
        "s": {
          "a": 0,
          "k": [
            100,
            100,
            100
          ],
          "ix": 6
        }
      },
      "ao": 0,
      "ip": 0,
      "op": 240,
      "st": 0,
      "bm": 0
    }
  ],
  "markers": []
}